hypothesis_auto/__init__.py
hypothesis_auto/pytest.py
hypothesis_auto/tester.py
hypothesis_auto-1.1.5.dist-info/LICENSE
hypothesis_auto-1.1.5.dist-info/WHEEL
hypothesis_auto-1.1.5.dist-info/METADATA
hypothesis_auto-1.1.5.dist-info/RECORD
