Metadata-Version: 2.1
Name: hypothesis-auto
Version: 1.1.5
Summary: Extends Hypothesis to add fully automatic testing of type annotated functions
License: MIT
Author: Timothy Crosley
Author-email: timothy.crosley@gmail.com
Requires-Python: >=3.6
Classifier: License :: OSI Approved :: MIT License
Classifier: Programming Language :: Python :: 3
Classifier: Programming Language :: Python :: 3.6
Classifier: Programming Language :: Python :: 3.7
Classifier: Programming Language :: Python :: 3.8
Classifier: Programming Language :: Python :: 3.9
Classifier: Programming Language :: Python :: 3.10
Classifier: Programming Language :: Python :: 3.11
Provides-Extra: pytest
Requires-Dist: hypothesis (>=4.36,<6.0.0)
Requires-Dist: pydantic (>=0.32.2,<2.0.0)
Requires-Dist: pytest (>=4.0.0); extra == "pytest"
